datasette_jellyfish/__init__.py
datasette_jellyfish-2.0.dist-info/LICENSE
datasette_jellyfish-2.0.dist-info/METADATA
datasette_jellyfish-2.0.dist-info/WHEEL
datasette_jellyfish-2.0.dist-info/entry_points.txt
datasette_jellyfish-2.0.dist-info/top_level.txt
datasette_jellyfish-2.0.dist-info/RECORD
