Metadata-Version: 2.1
Name: datasette-jellyfish
Version: 2.0
Summary: Datasette plugin adding SQL functions for fuzzy text matching powered by Jellyfish
Home-page: https://datasette.io/plugins/datasette-jellyfish
Author: Simon Willison
License: Apache License, Version 2.0
Project-URL: Issues, https://github.com/simonw/datasette-jellyfish/issues
Project-URL: CI, https://github.com/simonw/datasette-jellyfish/actions
Project-URL: Changelog, https://github.com/simonw/datasette-jellyfish/releases
License-File: LICENSE
Requires-Dist: datasette
Requires-Dist: jellyfish >0.9.0
Provides-Extra: test
Requires-Dist: pytest ; extra == 'test'
